Workbook

Sheet Resumo
A1: Conciliação DFC × DRE — 1º a 3º trimestre de 2026
A2: Diferença = caixa − competência, por conta, explicada motivo a motivo na aba Motivos. A conferência compara com a aba Calculos - V Eventos.
A4: Conta (DFC) | B4: Dif. 1º tri | C4: Dif. 2º tri | D4: Dif. 3º tri | F4: Conferência 1º | G4: Conferência 2º | H4: Conferência 3º | I4: Principais motivos
A5: Contas a receber de clientes | B5: =SUMIFS(Motivos!D:D,Motivos!$A:$A,$A5) | C5: =SUMIFS(Motivos!E:E,Motivos!$A:$A,$A5) | D5: =SUMIFS(Motivos!F:F,Motivos!$A:$A,$A5) | F5: =ROUND(B5-(-99757.5),0) | G5: =ROUND(C5-(-536434.2),0) | H5: =ROUND(D5-(173557.66),0) | I5: Rendimento dos fundos entra bruto na DRE e líquido de IR no caixa (−R$ 222-238 mil/tri, compensa em Impostos); royalties de 2025 recebidos em jan e jul; festa de arrecadação de maio bruta na DRE (−R$ 206 mil no 2º tri, compensa em Despesas Diretas); R$ 134 mil de correções de 2024 ("TESTE MARINA") no 2º tri.
A6: Ressarcíveis | B6: =SUMIFS(Motivos!D:D,Motivos!$A:$A,$A6) | C6: =SUMIFS(Motivos!E:E,Motivos!$A:$A,$A6) | D6: =SUMIFS(Motivos!F:F,Motivos!$A:$A,$A6) | F6: =ROUND(B6-(12279.01),0) | G6: =ROUND(C6-(14061.14),0) | H6: =ROUND(D6-(23625.63),0) | I6: Sem contrapartida na DRE (esperado: não é resultado).
A7: Estorno de pagamentos | B7: =SUMIFS(Motivos!D:D,Motivos!$A:$A,$A7) | C7: =SUMIFS(Motivos!E:E,Motivos!$A:$A,$A7) | D7: =SUMIFS(Motivos!F:F,Motivos!$A:$A,$A7) | F7: =ROUND(B7-(-228.02),0) | G7: =ROUND(C7-(697.46),0) | H7: =ROUND(D7-(2428.85),0) | I7: Sem contrapartida na DRE (esperado: não é resultado).
A8: Impostos e contribuições a recolher | B8: =SUMIFS(Motivos!D:D,Motivos!$A:$A,$A8) | C8: =SUMIFS(Motivos!E:E,Motivos!$A:$A,$A8) | D8: =SUMIFS(Motivos!F:F,Motivos!$A:$A,$A8) | F8: =ROUND(B8-(111208.58),0) | G8: =ROUND(C8-(196416.32),0) | H8: =ROUND(D8-(198303.31),0) | I8: IRPJ sobre rendimento dos fundos está na DRE mas é retido na fonte (+R$ 222-238 mil/tri); IRPJ/CSLL pago um trimestre depois; DAS de SPDX/Dataforte inclui o INSS delas; parcelamento antigo da SPDX.
A9: Salários, provisões e encargos sociais | B9: =SUMIFS(Motivos!D:D,Motivos!$A:$A,$A9) | C9: =SUMIFS(Motivos!E:E,Motivos!$A:$A,$A9) | D9: =SUMIFS(Motivos!F:F,Motivos!$A:$A,$A9) | F9: =ROUND(B9-(-60078.54),0) | G9: =ROUND(C9-(248415.54),0) | H9: =ROUND(D9-(-257657.96),0) | I9: PLR e bônus pagos por semestre (jan/fev e jul) contra provisão mensal na DRE; 13º provisionado (+R$ 70 mil/tri); folha paga no mês seguinte.
A10: Devoluções de Vendas | B10: =SUMIFS(Motivos!D:D,Motivos!$A:$A,$A10) | C10: =SUMIFS(Motivos!E:E,Motivos!$A:$A,$A10) | D10: =SUMIFS(Motivos!F:F,Motivos!$A:$A,$A10) | F10: =ROUND(B10-(0.0),0) | G10: =ROUND(C10-(120000.0),0) | H10: =ROUND(D10-(0.0),0) | I10: Devolução de R$ 120 mil na DRE de junho sem saída de caixa — a verificar.
A11: Despesas Diretas | B11: =SUMIFS(Motivos!D:D,Motivos!$A:$A,$A11) | C11: =SUMIFS(Motivos!E:E,Motivos!$A:$A,$A11) | D11: =SUMIFS(Motivos!F:F,Motivos!$A:$A,$A11) | F11: =ROUND(B11-(-31484.4),0) | G11: =ROUND(C11-(210112.53),0) | H11: =ROUND(D11-(-146718.7),0) | I11: Custo da festa de maio bruto na DRE (+R$ 178 mil no 2º tri); Conviva 2026 pago acima do reconhecido (−R$ 107 mil no 3º tri); comissões em lote, inclusive da V Company.
A12: Despesas Administrativas | B12: =SUMIFS(Motivos!D:D,Motivos!$A:$A,$A12) | C12: =SUMIFS(Motivos!E:E,Motivos!$A:$A,$A12) | D12: =SUMIFS(Motivos!F:F,Motivos!$A:$A,$A12) | F12: =ROUND(B12-(29949.23),0) | G12: =ROUND(C12-(43576.28),0) | H12: =ROUND(D12-(-5136.24),0) | I12: Softwares de jan na DRE acima do pago; aluguel pago no mês seguinte.
A13: Vendas e Marketing | B13: =SUMIFS(Motivos!D:D,Motivos!$A:$A,$A13) | C13: =SUMIFS(Motivos!E:E,Motivos!$A:$A,$A13) | D13: =SUMIFS(Motivos!F:F,Motivos!$A:$A,$A13) | F13: =ROUND(B13-(-20542.25),0) | G13: =ROUND(C13-(-30211.35),0) | H13: =ROUND(D13-(-278.16),0) | I13: Categorias "Marketing (*)" e "Bonificações (*)" não aparecem na linha da DRE.
A14: Receitas não operacionais | B14: =SUMIFS(Motivos!D:D,Motivos!$A:$A,$A14) | C14: =SUMIFS(Motivos!E:E,Motivos!$A:$A,$A14) | D14: =SUMIFS(Motivos!F:F,Motivos!$A:$A,$A14) | F14: =ROUND(B14-(462.8),0) | G14: =ROUND(C14-(-17702.63),0) | H14: =ROUND(D14-(-51498.72),0) | I14: Bloqueio judicial de R$ 64,7 mil em set lançado aqui.
A15: Despesas Financeiras / Bancos | B15: =SUMIFS(Motivos!D:D,Motivos!$A:$A,$A15) | C15: =SUMIFS(Motivos!E:E,Motivos!$A:$A,$A15) | D15: =SUMIFS(Motivos!F:F,Motivos!$A:$A,$A15) | F15: =ROUND(B15-(205.6),0) | G15: =ROUND(C15-(-6851.97),0) | H15: =ROUND(D15-(-2197.59),0) | I15: IR sobre aplicações sem linha na DRE.
A16: Doações | B16: =SUMIFS(Motivos!D:D,Motivos!$A:$A,$A16) | C16: =SUMIFS(Motivos!E:E,Motivos!$A:$A,$A16) | D16: =SUMIFS(Motivos!F:F,Motivos!$A:$A,$A16) | F16: =ROUND(B16-(0.0),0) | G16: =ROUND(C16-(0.0),0) | H16: =ROUND(D16-(-10370.78),0) | I16: Doações pagas pela V Company em set.
A17: Dividendos Pagos | B17: =SUMIFS(Motivos!D:D,Motivos!$A:$A,$A17) | C17: =SUMIFS(Motivos!E:E,Motivos!$A:$A,$A17) | D17: =SUMIFS(Motivos!F:F,Motivos!$A:$A,$A17) | F17: =ROUND(B17-(-385986.69),0) | G17: =ROUND(C17-(-175775.42),0) | H17: =ROUND(D17-(-933658.45),0) | I17: Sem contrapartida na DRE (esperado: não é resultado).
A18: P&D | B18: =SUMIFS(Motivos!D:D,Motivos!$A:$A,$A18) | C18: =SUMIFS(Motivos!E:E,Motivos!$A:$A,$A18) | D18: =SUMIFS(Motivos!F:F,Motivos!$A:$A,$A18) | F18: =ROUND(B18-(42.96),0) | G18: =ROUND(C18-(2225.94),0) | H18: =ROUND(D18-(364.45),0) | I18: Só na DRE.
A19: Aquisição de imobilizado e intangível | B19: =SUMIFS(Motivos!D:D,Motivos!$A:$A,$A19) | C19: =SUMIFS(Motivos!E:E,Motivos!$A:$A,$A19) | D19: =SUMIFS(Motivos!F:F,Motivos!$A:$A,$A19) | F19: =ROUND(B19-(-8443.05),0) | G19: =ROUND(C19-(-17902.2),0) | H19: =ROUND(D19-(-10692.53),0) | I19: Sem contrapartida na DRE (esperado: não é resultado).
A20: Aumento de Capital | B20: =SUMIFS(Motivos!D:D,Motivos!$A:$A,$A20) | C20: =SUMIFS(Motivos!E:E,Motivos!$A:$A,$A20) | D20: =SUMIFS(Motivos!F:F,Motivos!$A:$A,$A20) | F20: =ROUND(B20-(37175.2),0) | G20: =ROUND(C20-(0.0),0) | H20: =ROUND(D20-(0.0),0) | I20: Sem contrapartida na DRE (esperado: não é resultado).
A21: Outras despesas | B21: =SUMIFS(Motivos!D:D,Motivos!$A:$A,$A21) | C21: =SUMIFS(Motivos!E:E,Motivos!$A:$A,$A21) | D21: =SUMIFS(Motivos!F:F,Motivos!$A:$A,$A21) | F21: =ROUND(B21-(0.0),0) | G21: =ROUND(C21-(0.0),0) | H21: =ROUND(D21-(16511.94),0) | I21: Sem contrapartida na DRE (esperado: não é resultado).
A22: Mútuos | B22: =SUMIFS(Motivos!D:D,Motivos!$A:$A,$A22) | C22: =SUMIFS(Motivos!E:E,Motivos!$A:$A,$A22) | D22: =SUMIFS(Motivos!F:F,Motivos!$A:$A,$A22) | F22: =ROUND(B22-(73446.43),0) | G22: =ROUND(C22-(15263.71),0) | H22: =ROUND(D22-(232622.81),0) | I22: Sem contrapartida na DRE (esperado: não é resultado).
A23: Dividendos recebidos | B23: =SUMIFS(Motivos!D:D,Motivos!$A:$A,$A23) | C23: =SUMIFS(Motivos!E:E,Motivos!$A:$A,$A23) | D23: =SUMIFS(Motivos!F:F,Motivos!$A:$A,$A23) | F23: =ROUND(B23-(0.0),0) | G23: =ROUND(C23-(60000.0),0) | H23: =ROUND(D23-(49000.0),0) | I23: Sem contrapartida na DRE (esperado: não é resultado).
A24: Total (= aumento/redução de caixa − lucro) | B24: =SUM(B5:B23) | C24: =SUM(C5:C23) | D24: =SUM(D5:D23)
A26: Por tipo de motivo
A27: Tipo | B27: Dif. 1º tri | C27: Dif. 2º tri | D27: Dif. 3º tri
A28: Prazo | B28: =SUMIFS(Motivos!D:D,Motivos!$C:$C,$A28) | C28: =SUMIFS(Motivos!E:E,Motivos!$C:$C,$A28) | D28: =SUMIFS(Motivos!F:F,Motivos!$C:$C,$A28) | I28: Competência × caixa: o mesmo valor cai em trimestres diferentes. É a variação de capital de giro que o DFC indireto existe para mostrar.
A29: Provisão da DRE | B29: =SUMIFS(Motivos!D:D,Motivos!$C:$C,$A29) | C29: =SUMIFS(Motivos!E:E,Motivos!$C:$C,$A29) | D29: =SUMIFS(Motivos!F:F,Motivos!$C:$C,$A29) | I29: 13º e férias provisionados mês a mês, pagos depois.
A30: Bruto × líquido | B30: =SUMIFS(Motivos!D:D,Motivos!$C:$C,$A30) | C30: =SUMIFS(Motivos!E:E,Motivos!$C:$C,$A30) | D30: =SUMIFS(Motivos!F:F,Motivos!$C:$C,$A30) | I30: Rendimento dos fundos e festa de maio: bruto na DRE, líquido no caixa. As contas se compensam entre si.
A31: Classificação | B31: =SUMIFS(Motivos!D:D,Motivos!$C:$C,$A31) | C31: =SUMIFS(Motivos!E:E,Motivos!$C:$C,$A31) | D31: =SUMIFS(Motivos!F:F,Motivos!$C:$C,$A31) | I31: Item em vínculo diferente da linha equivalente da DRE, ou categoria sem mapeamento.
A32: Não é caixa do período | B32: =SUMIFS(Motivos!D:D,Motivos!$C:$C,$A32) | C32: =SUMIFS(Motivos!E:E,Motivos!$C:$C,$A32) | D32: =SUMIFS(Motivos!F:F,Motivos!$C:$C,$A32) | I32: Correções de saldo de 2024 lançadas em abr/2026.
A33: Escopo (V Company) | B33: =SUMIFS(Motivos!D:D,Motivos!$C:$C,$A33) | C33: =SUMIFS(Motivos!E:E,Motivos!$C:$C,$A33) | D33: =SUMIFS(Motivos!F:F,Motivos!$C:$C,$A33) | I33: Pagamentos da V Company que a DRE não acompanha.
A34: A verificar | B34: =SUMIFS(Motivos!D:D,Motivos!$C:$C,$A34) | C34: =SUMIFS(Motivos!E:E,Motivos!$C:$C,$A34) | D34: =SUMIFS(Motivos!F:F,Motivos!$C:$C,$A34) | I34: Diferenças que dependem de confirmação (ver aba Motivos).
A35: Sem DRE (por natureza) | B35: =SUMIFS(Motivos!D:D,Motivos!$C:$C,$A35) | C35: =SUMIFS(Motivos!E:E,Motivos!$C:$C,$A35) | D35: =SUMIFS(Motivos!F:F,Motivos!$C:$C,$A35) | I35: Dividendos, mútuos, imobilizado, capital, parcelamento, bloqueio judicial: não são resultado.
A36: Total | B36: =SUM(B28:B35) | C36: =SUM(C28:C35) | D36: =SUM(D28:D35)

Sheet Motivos
A1: Conta (DFC) | B1: Motivo | C1: Tipo | D1: Dif. 1º tri | E1: Dif. 2º tri | F1: Dif. 3º tri | G1: Total | H1: O que explica | I1: O que fazer
A2: Contas a receber de clientes | B2: Rendimento dos fundos (Receita SPDX): IR retido na fonte | C2: Bruto × líquido | D2: -222036.33 | E2: -236273.64 | F2: -237894.64 | G2: =SUM(D2:F2) | H2: A DRE reconhece o rendimento BRUTO dos fundos de formatura ("Receita SPDX") e lança o IR à parte ("IRPJ - Rendimentos", ~16,3% todo mês). No caixa o rendimento chega LÍQUIDO (saque da conta Unificada para a SPDX), então o IR nunca aparece como pagamento. Compensa exatamente a diferença positiva da conta Impostos. | I2: Nada a corrigir; ler junto com Impostos (o efeito líquido das duas é zero).
A3: Contas a receber de clientes | B3: Royalties de competência 2025 recebidos em 2026 | C3: Prazo | D3: 169985.07 | E3: 16097.98 | F3: 90347.9 | G3: =SUM(D3:F3) | H3: Recebimentos de royalties cuja observação cita competência de 2025 (ex.: "TIT. LIQUIDADO DE DEZEMBRO DE 2025", "COMPETÊNCIA SETEMBRO, OUTUBRO, NOVEMBRO DE 2025"). Já estavam na DRE de 2025; entram no caixa de 2026. É o mínimo identificável: a maioria dos recebimentos está com observação "N/D". | I3: Nada a corrigir.
A4: Contas a receber de clientes | B4: Festa de arrecadação de maio contabilizada bruta | C4: Bruto × líquido | D4: 2034.07 | E4: -205790.53 | F4: 48341.33 | G4: =SUM(D4:F4) | H4: A DRE de maio tem R$ 263,5 mil de receita e R$ 188,6 mil de custo de festa de arrecadação. No caixa das empresas entrou só a margem (~R$ 69 mil, Dataforte em jun): receita e custo passaram pelas contas do fundo. Compensa a diferença positiva de Despesas Diretas. | I4: Nada a corrigir; ler junto com Despesas Diretas.
A5: Contas a receber de clientes | B5: Royalties: demais diferenças de prazo (faturado × recebido) | C5: Prazo | D5: 2456.92 | E5: -82095.68 | F5: 158481.79 | G5: =SUM(D5:F5) | H5: Royalty recorrente (4,7% dos títulos liquidados) é reconhecido na competência e recebido com atraso; no 2º tri o recebido ficou abaixo do reconhecido e foi recuperado no 3º. Inclui royalties recebidos pela V Company (R$ 68/66/26 mil por tri). | I5: Nada a corrigir; acompanhar o saldo a receber de royalties.
A6: Contas a receber de clientes | B6: Receitas sem linha na DRE lançadas como "Contas a receber" | C6: Classificação | D6: 34059.33 | E6: 30118.11 | F6: 92361.86 | G6: =SUM(D6:F6) | H6: Rendimentos de aplicações financeiras (R$ 23/25/35 mil), "Serviços prestados a fornecedores da rede" (R$ 56 mil em ago-set) e "Receita não operacional (inativa)" da V Company. Não são recebimento de cliente. | I6: Reclassificar rendimentos de aplicação para um vínculo próprio (resultado financeiro).
A7: Contas a receber de clientes | B7: Markup de tarifas recebido no mês seguinte | C7: Prazo | D7: -81491.56 | E7: -14857.99 | F7: 46614.09 | G7: =SUM(D7:F7) | H7: O markup de um mês é recebido (pela Dataforte) exatamente no mês seguinte: o caixa de fev (R$ 175.537) é a competência de jan. Cada trimestre de caixa carrega o último mês do trimestre anterior. | I7: Nada a corrigir.
A8: Contas a receber de clientes | B8: Taxas de franquia (inicial e renovação) | C8: A verificar | D8: 78250 | E8: 41511.01 | F8: 20150 | G8: =SUM(D8:F8) | H8: A DRE só reconheceu taxa de franquia em set (R$ 60 mil). O caixa recebeu parcelas de taxas iniciais de contratos anteriores (R$ 3.250/mês + parcelas avulsas) e R$ 60 mil de RENOVAÇÕES (jan, fev, mai, set) — a linha "Renovação de Franquias" da DRE está zerada o ano todo. | I8: Confirmar se a renovação deveria estar na DRE de 2026.
A9: Contas a receber de clientes | B9: Correções de saldo de cartão de 2024 ("TESTE MARINA") | C9: Não é caixa do período | D9: 0 | E9: -134474.42 | F9: 0 | G9: =SUM(D9:F9) | H9: Sete lançamentos de abr/2026 na V Company (Cartão Vitor Santander / Vitor PF Santander) que corrigem diferenças de faturas de 2024 ("diferença lançada na data de hoje para correção do saldo"). Não é movimento de caixa de 2026. | I9: Excluir do DFC de 2026 (ou mover para ajuste de saldo inicial).
A10: Contas a receber de clientes | B10: Rendimento dos fundos: saque no mês seguinte | C10: Prazo | D10: -108629.75 | E10: 18342.05 | F10: 1493.2 | G10: =SUM(D10:F10) | H10: O rendimento do mês M é sacado em M+1 ou depois (dez/25 sacado em jan; mar sacado em abr; jun sacado em ago; set ainda não sacado). Inclui os R$ 31,6 mil/mês que entram pela V Company ("Conciliação saque de rendimento"). Somando as duas partes, o saque bate 98-99% do rendimento líquido da DRE, mês a mês. | I10: Nada a corrigir (é variação de capital de giro).
A11: Contas a receber de clientes | B11: Fundo de Marketing, Taxa Mundo Viva, Assessoria CSC e Projetos | C11: Prazo | D11: 25614.75 | E11: 32538.98 | F11: 32413.93 | G11: =SUM(D11:F11) | H11: Pequenas diferenças de prazo e alguns recebimentos da V Company (assessoria, taxa) que não estão na DRE. | I11: Nada a corrigir.
A12: Contas a receber de clientes | B12: Outras transferências sem contrapartida | C12: A verificar | D12: 0 | E12: -1550.07 | F12: -78751.79 | G12: =SUM(D12:F12) | H12: 3º tri: PIX de R$ 85 mil enviado pela V E em 16/07 ("PIX ENVIADO ... V EVENTOS BRASIL LTDA") sem a entrada correspondente; ida e volta de R$ 600 mil com a conta Unificada XP/Sicoob (sobra R$ 8,3 mil de distribuição de sobras do Sicoob); depósito de R$ 1 mil na conta garantia do Omie.CASH. 2º tri: R$ 1,5 mil Efi → SOS. | I12: Localizar a conta de destino do PIX de R$ 85 mil; se for conta do grupo fora do escopo, tratar como transferência.
A13: Ressarcíveis | B13: Despesas pagas em nome dos franqueados e reembolsadas | C13: Sem DRE (por natureza) | D13: 12279.01 | E13: 14061.14 | F13: 23625.63 | G13: =SUM(D13:F13) | H13: Softwares e outras despesas pagas pela rede e reembolsadas pelos franqueados. O reembolsado supera o pago (R$ 12/14/24 mil por tri). | I13: Nada a corrigir.
... A51: Dividendos recebidos | B51: Dividendos recebidos pela V Company | C51: Sem DRE (por natureza) | D51: 0 | E51: 60000 | F51: 49000 | G51: =SUM(D51:F51) | H51: Não passa pela DRE do grupo. | I51: Nada a corrigir.
A53: Diferença = caixa (aba Lançamentos VE 2026) − competência (aba Viva Company), o mesmo sinal da aba Calculos - V Eventos. Valores calculados a partir da planilha DFC - Viva Company 2026.xlsx em 26/10/2026.

Sheet DRE x Caixa por linha
A1: Conta (DFC) | B1: Linha da DRE / categoria do caixa | C1: Tipo | D1: DRE 1º | E1: Caixa 1º | F1: Dif. 1º | G1: DRE 2º | H1: Caixa 2º | I1: Dif. 2º | J1: DRE 3º | K1: Caixa 3º | L1: Dif. 3º
A2: Contas a receber de clientes | B2: Royalties (recorrentes + fechamentos) | C2: na DRE | D2: 2064034.9 | E2: 2236476.9 | F2: =E2-D2 | G2: 1903668.8 | H2: 1837671.1 | I2: =H2-G2 | J2: 1874846.1 | K2: 2123675.8 | L2: =K2-J2
A3: Contas a receber de clientes | B3: Fundo de Marketing | C3: na DRE | D3: 129792.51 | E3: 142932.83 | F3: =E3-D3 | G3: 119928.95 | H3: 118332.51 | I3: =H3-G3 | J3: 115839.23 | K3: 132127.82 | L3: =K3-J3
A4: Contas a receber de clientes | B4: Taxas de Franquia | C4: na DRE | D4: 0 | E4: 78250 | F4: =E4-D4 | G4: 0 | H4: 41511.01 | I4: =H4-G4 | J4: 60000 | K4: 80150 | L4: =K4-J4
A5: Contas a receber de clientes | B5: Receita SPDX (rendimento dos fundos) | C5: na DRE | D5: 1358482.8 | E5: 932991.91 | F5: =E5-D5 | G5: 1460043.8 | H5: 1147287.4 | I5: =H5-G5 | J5: 1467401.3 | K5: 1136440 | L5: =K5-J5
A6: Contas a receber de clientes | B6: Taxa Mundo Viva | C6: na DRE | D6: 220369.6 | E6: 233126.54 | F6: =E6-D6 | G6: 217789.4 | H6: 247533.83 | I6: =H6-G6 | J6: 231613.8 | K6: 243131.88 | L6: =K6-J6
A7: Contas a receber de clientes | B7: Markup de Tarifas | C7: na DRE | D7: 396374.11 | E7: 314882.55 | F7: =E7-D7 | G7: 363299.51 | H7: 348441.52 | I7: =H7-G7 | J7: 362765.48 | K7: 409379.57 | L7: =K7-J7
A8: Contas a receber de clientes | B8: Festas de Arrecadação | C8: na DRE | D8: 16841.72 | E8: 18875.79 | F8: =E8-D8 | G8: 282741.45 | H8: 76950.92 | I8: =H8-G8 | J8: 25540.72 | K8: 73882.05 | L8: =K8-J8
A9: Contas a receber de clientes | B9: Receita com Projetos | C9: na DRE | D9: 3987.3722 | E9: 3704.86 | F9: =E9-D9 | G9: 1352.0153 | H9: 1567.6 | I9: =H9-G9 | J9: 3233.4026 | K9: 3477.66 | L9: =K9-J9
A10: Contas a receber de clientes | B10: Assessoria CSC | C10: na DRE | D10: 228760.37 | E10: 228760.37 | F10: =E10-D10 | G10: 226066.04 | H10: 230241.45 | I10: =H10-G10 | J10: 223923.26 | K10: 228286.26 | L10: =K10-J10
A11: Contas a receber de clientes | B11: Clientes - Serviços Prestados a Fornecedores Rede [VCO] | C11: sem DRE | D11: 0 | E11: 8505 | F11: =E11-D11 | G11: 0 | H11: 3495 | I11: =H11-G11 | J11: 0 | K11: 0 | L11: =K11-J11
A12: Contas a receber de clientes | B12: Clientes - Serviços Prestados a Fornecedores Rede [VE] | C12: sem DRE | D12: 0 | E12: 0 | F12: =E12-D12 | G12: 0 | H12: 0 | I12: =H12-G12 | J12: 0 | K12: 56077.5 | L12: =K12-J12
A13: Contas a receber de clientes | B13: Entrada de Transferência (*) [VE] | C13: sem DRE | D13: 0 | E13: 0 | F13: =E13-D13 | G13: 0 | H13: 490000 | I13: =H13-G13 | J13: 0 | K13: 2085925.5 | L13: =K13-J13
... A87: Receitas não operacionais | B87: Bloqueio Judicial [VE] | C87: sem DRE | D87: 0 | E87: 0 | F87: =E87-D87 | G87: 0 | H87: 0 | I87: =H87-G87 | J87: 0 | K87: -64708.41 | L87: =K87-J87
A89: Transferências aparecem com entrada e saída separadas por empresa; entre contas do grupo elas se anulam. "Receita SPDX" é comparada ao saque de rendimento das contas Unificadas.

Sheet Ajustes sugeridos
A1: # | B1: Onde | C1: O que fazer | D1: Por quê | E1: Valor (R$)
A2: 1 | B2: Lançamentos — V Company, abr/2026, "Saída de Transferência (*)", obs. "TESTE MARINA" | C2: Excluir do DFC de 2026 (ou tratar como ajuste de saldo inicial). | D2: São correções de saldo de faturas de cartão de 2024, não movimento de caixa de 2026. Distorcem Contas a receber do 2º tri. | E2: -134474.42
A3: 2 | B3: Lançamentos — V E, 16/07, PIX enviado de R$ 85 mil ("PIX ENVIADO 1607 1547 V EVENTOS BRASIL LTDA") | C3: Identificar a conta de destino. | D3: Saída de transferência sem entrada correspondente em nenhuma conta da planilha. | E3: -85000
A4: 3 | B4: Lançamentos — Bloqueio judicial (set) e Desbloqueio judicial (set) | C4: Lançar os dois no mesmo vínculo (ex.: "Depósitos judiciais"). | D4: Hoje o bloqueio está em Receitas não operacionais e o desbloqueio em Outras despesas. | E4: -47396
A5: 4 | B5: Lançamentos — Rendimentos de Aplicações | C5: Tirar de "Contas a receber de clientes" e criar um vínculo de resultado financeiro. | D5: É receita financeira, não recebimento de cliente. | E5: 82677.76
A6: 5 | B6: Lançamentos — Comissões de set em "Salários, provisões e encargos sociais" | C6: Mover para Despesas Diretas. | D6: Na DRE, comissão é custo direto. | E6: -21000
A7: 6 | B7: Omie — plano de saúde Sabin Sinai na categoria "Pró Labore Sócios" | C7: Usar a categoria de Assistência Médica. | D7: Mensalidade e coparticipação estão saindo como pró-labore.
A8: 7 | B8: DRE — mapeamento de categorias | C8: Incluir na DRE: "Marketing (*)", "Bonificações (*)", "Cobertura Fotográfica", "Assistência Médica / Salários" e "/ Pró Labore", e conferir a linha "Renovação de Franquias" (zerada o ano todo, mas houve R$ 60 mil recebidos). | D8: São despesas e receitas recorrentes que só aparecem no caixa.
A9: 8 | B9: DRE — devolução de vendas de jun (R$ 120,3 mil) | C9: Confirmar se foi estorno de receita sem devolução de dinheiro ou se ainda vai ser paga. | D9: Não houve saída de caixa correspondente até set. | E9: 120000
A10: 9 | B10: DRE — IRPJ/CSLL do 2º tri | C10: Conferir a estimativa (R$ 236 mil) contra a guia paga em julho (R$ 147 mil). | D10: A DRE pode estar superestimando o imposto do trimestre. | E10: 89625
A11: 10 | B11: DRE — Contratados PJ | C11: Localizar em que categoria os PJ estão sendo pagos. | D11: A DRE tem R$ 143 mil de PJ em 9 meses; a categoria no caixa soma R$ 52 mil. | E11: 90952
A12: 11 | B12: Leitura do DFC — rendimento dos fundos | C12: Ler Contas a receber e Impostos juntos (ou levar o IRPJ - Rendimentos para dentro de Contas a receber). | D12: O IR de ~16,3% do rendimento aparece como diferença negativa numa conta e positiva na outra.
A13: 12 | B13: Leitura do DFC — INSS de SPDX e Dataforte | C13: Comparar Impostos + INSS juntos. | D13: A DRE põe o INSS dessas empresas em Pessoal; o caixa paga dentro do DAS, em Impostos.
A15: Valor = impacto aproximado no caixa ou na diferença da conta, conforme o item. Itens sem valor são de mapeamento.
